poffertjes/__init__.py
poffertjes/calculator.py
poffertjes/exceptions.py
poffertjes/expression.py
poffertjes/p_interface.py
poffertjes/query_builder.py
poffertjes/result.py
poffertjes/variable.py
poffertjes-0.2.0.dist-info/METADATA
poffertjes-0.2.0.dist-info/WHEEL
poffertjes-0.2.0.dist-info/entry_points.txt
poffertjes-0.2.0.dist-info/RECORD
