Metadata-Version: 2.4
Name: poffertjes
Version: 0.2.0
Summary: Friendly, pythonic interface for probabilistic queries on dataframes
Author-email: Silvio Lugaro <silvio.lugaro@gmail.com>
Keywords: dataframes,pandas,polars,probability,statistics
Requires-Python: >=3.13
Requires-Dist: loguru>=0.7.3
Requires-Dist: marimo>=0.13.10
Requires-Dist: narwhals>=1.0.0
Requires-Dist: pandas>=2.2.3
Requires-Dist: plotly==6.4.0
Requires-Dist: pyarrow>=20.0.0
Requires-Dist: ruff>=0.11.10
Provides-Extra: dev
Requires-Dist: hypothesis>=6.0.0; extra == 'dev'
Requires-Dist: polars>=1.0.0; extra == 'dev'
Requires-Dist: pytest>=8.0.0; extra == 'dev'
